{
	"__comment": "~ Elsweyr",
	"textures": {
		"texture": "paragonia:blocks/decorations/journal",
        "particle": "paragonia:blocks/decorations/journal"
	},
	"elements": [ 	 
		{
			"__comment": "Journal",
			"from": [ 4, 0, 2 ],
			"to": [ 12, 2, 14 ],
            "rotation": { "origin": [ 8, 8, 8 ], "axis": "y", "angle": 45 },
			"faces": {
				"down": { "uv": [ 11, 16, 7, 10 ], "texture": "#texture", "rotation": 180 },
				"up": { "uv": [ 12, 10, 16, 16 ], "texture": "#texture", "rotation": 180 },
				"north": { "uv": [ 12, 9, 16, 10 ], "texture": "#texture" },
				"south": { "uv": [ 12, 9, 16, 10 ], "texture": "#texture" },
				"west": { "uv": [ 7, 10, 6, 16 ], "texture": "#texture", "rotation": 90 },
				"east": { "uv": [ 11, 10, 12, 16 ], "texture": "#texture", "rotation": 270 }
			}
		}
	],
	"display": {
		"thirdperson_righthand": {
			"rotation":  [ 6, 0, -92 ],
			"translation":  [ 5.4809, -1.421, 0 ],
			"scale":  [ 0.75, 0.75, 0.75 ]
		},
		"thirdperson_lefthand": {
			"rotation":  [ 6, 0, -92 ],
			"translation":  [ 5.4809, -1.421, 0 ],
			"scale":  [ 0.75, 0.75, 0.75 ]
		},
		"firstperson_righthand": {
			"rotation":  [ 93, 0, 76 ],
			"translation":  [ -3.027, -2.417, 0 ]
		},
		"firstperson_lefthand": {
			"rotation":  [ 93, 0, 76 ],
			"translation":  [ -3.027, -2.417, 0 ]
		},
		"gui": {
			"rotation":  [ 39, 156, 0 ],
			"translation":  [ 0, 4.663, 0 ]
		},
		"head": {
			"translation":  [ 0, -31.53, 0 ],
			"scale":  [ 1.5, 1.5, 1.5 ]
		},
		"ground": {
			"translation":  [ 0, 5.1087, 0 ]
		}
	}
}